Metadata-Version: 2.4
Name: blobify
Version: 1.1.0
Summary: Package your entire codebase into a single text file for AI consumption
Author-email: Alexander Parker <pypi@parker.im>
Maintainer-email: Alexander Parker <pypi@parker.im>
License-Expression: MIT
Project-URL: Author, https://parker.im
Project-URL: Documentation, https://github.com/AlexanderParker/blobify#readme
Project-URL: Repository, https://github.com/AlexanderParker/blobify
Project-URL: Bug Reports, https://github.com/AlexanderParker/blobify/issues
Project-URL: Feature Requests, https://github.com/AlexanderParker/blobify/issues
Project-URL: VS Code Extension, https://marketplace.visualstudio.com/items?itemName=ShentonConsulting.blobify-format
Keywords: ai,llm,chatgpt,claude,codebase,code-analysis,text-processing,file-aggregation,developer-tools,automation,documentation,code-review,refactoring,context-engineering
Classifier: Development Status :: 4 - Beta
Classifier: Intended Audience :: Developers
Classifier: Intended Audience :: Information Technology
Classifier: Topic :: Software Development :: Documentation
Classifier: Topic :: Software Development :: Libraries :: Python Modules
Classifier: Topic :: Text Processing :: General
Classifier: Topic :: Utilities
Classifier: Programming Language :: Python :: 3
Classifier: Programming Language :: Python :: 3.10
Classifier: Programming Language :: Python :: 3.11
Classifier: Programming Language :: Python :: 3.12
Classifier: Programming Language :: Python :: 3.13
Classifier: Operating System :: OS Independent
Classifier: Environment :: Console
Classifier: Natural Language :: English
Classifier: Typing :: Typed
Requires-Python: >=3.10
License-File: LICENSE
Requires-Dist: rich>=14.1.0
Requires-Dist: scrubadub>=2.0.1
Provides-Extra: dev
Requires-Dist: invoke>=2.2.0; extra == "dev"
Requires-Dist: black>=25.1.0; extra == "dev"
Requires-Dist: isort>=6.0.1; extra == "dev"
Requires-Dist: flake8>=7.3.0; extra == "dev"
Requires-Dist: Flake8-pyproject>=1.2.3; extra == "dev"
Requires-Dist: flake8-bugbear>=24.12.12; extra == "dev"
Requires-Dist: pep8-naming>=0.15.1; extra == "dev"
Requires-Dist: pytest>=8.4.1; extra == "dev"
Requires-Dist: pytest-cov>=6.2.1; extra == "dev"
Requires-Dist: pre-commit>=4.2.0; extra == "dev"
Requires-Dist: unittest-xml-reporting>=3.2.0; extra == "dev"
Requires-Dist: tomli-w>=1.2.0; extra == "dev"
Requires-Dist: build>=1.3.0; extra == "dev"
Requires-Dist: twine>=6.1.0; extra == "dev"
Dynamic: license-file
